
[
{"pk_i_id":"1","capacity":"1","ampere":"32","customer_type":"4","fk_i_customer_id":"4","s_mobile":"0595105417","BusinessName":"test2","AddressDetailsAR":"   etst2","d_lat":"0","d_lng":"0","ownership_type":"1","owner_type":"i","owner_id":"0","licno":"2345","fk_i_created_by":"6","dt_created_at":"2021-09-23 08:48:22","fk_i_dept_id":"7","customer_name":"غالب عوض  عبد الرحمن صالح ","s_attach1":"","s_attach2":"","connected_to":"0","ReciptNo":null,"AmountInNIS":null,"json_fees":"{\"\\u0631\\u0633\\u0648\\u0645 \\u0627\\u0644\\u0625\\u0634\\u062a\\u0631\\u0627\\u0643\":\"1000\",\"\\u0631\\u0633\\u0648\\u0645 \\u062a\\u0642\\u062f\\u064a\\u0645 \\u0637\\u0644\\u0628\":\"100\",\"\\u062b\\u0645\\u0646 \\u0627\\u0644\\u0639\\u062f\\u0627\\u062f\":\"550\",\"\\u062b\\u0645\\u0646 \\u0645\\u0631\\u0627\\u0628\\u0637\":\"47\",\"\\u0644\\u0648\\u0627\\u0632\\u0645 \\u062a\\u0645\\u062f\\u064a\\u062f\":\"2\"}","owner_name":""},
{"pk_i_id":"2","capacity":"1","ampere":"32","customer_type":"4","fk_i_customer_id":"4","s_mobile":"0595105417","BusinessName":"test2","AddressDetailsAR":"   etst2","d_lat":"0","d_lng":"0","ownership_type":"1","owner_type":"i","owner_id":"0","licno":"2345","fk_i_created_by":"6","dt_created_at":"2021-09-23 08:49:03","fk_i_dept_id":"7","customer_name":"غالب عوض  عبد الرحمن صالح ","s_attach1":"","s_attach2":"","connected_to":"0","ReciptNo":null,"AmountInNIS":null,"json_fees":"{\"\\u0631\\u0633\\u0648\\u0645 \\u0627\\u0644\\u0625\\u0634\\u062a\\u0631\\u0627\\u0643\":\"1000\",\"\\u0631\\u0633\\u0648\\u0645 \\u062a\\u0642\\u062f\\u064a\\u0645 \\u0637\\u0644\\u0628\":\"100\",\"\\u062b\\u0645\\u0646 \\u0627\\u0644\\u0639\\u062f\\u0627\\u062f\":\"550\",\"\\u062b\\u0645\\u0646 \\u0645\\u0631\\u0627\\u0628\\u0637\":\"47\",\"\\u0644\\u0648\\u0627\\u0632\\u0645 \\u062a\\u0645\\u062f\\u064a\\u062f\":\"2\"}","owner_name":""},
{"pk_i_id":"3","capacity":"1","ampere":"32","customer_type":"4","fk_i_customer_id":"4","s_mobile":"0595105417","BusinessName":"test2","AddressDetailsAR":"   etst2","d_lat":"0","d_lng":"0","ownership_type":"1","owner_type":"i","owner_id":"0","licno":"2345","fk_i_created_by":"6","dt_created_at":"2021-09-23 08:49:08","fk_i_dept_id":"7","customer_name":"غالب عوض  عبد الرحمن صالح ","s_attach1":"","s_attach2":"","connected_to":"0","ReciptNo":null,"AmountInNIS":null,"json_fees":"{\"\\u0631\\u0633\\u0648\\u0645 \\u0627\\u0644\\u0625\\u0634\\u062a\\u0631\\u0627\\u0643\":\"1000\",\"\\u0631\\u0633\\u0648\\u0645 \\u062a\\u0642\\u062f\\u064a\\u0645 \\u0637\\u0644\\u0628\":\"100\",\"\\u062b\\u0645\\u0646 \\u0627\\u0644\\u0639\\u062f\\u0627\\u062f\":\"550\",\"\\u062b\\u0645\\u0646 \\u0645\\u0631\\u0627\\u0628\\u0637\":\"47\",\"\\u0644\\u0648\\u0627\\u0632\\u0645 \\u062a\\u0645\\u062f\\u064a\\u062f\":\"2\"}","owner_name":""},
{"pk_i_id":"4","capacity":"1","ampere":"32","customer_type":"8","fk_i_customer_id":"842","s_mobile":"0599593024","BusinessName":"","AddressDetailsAR":"   منطقة الكرايم قيد الانشاء ","d_lat":"0","d_lng":"0","ownership_type":"1","owner_type":"i","owner_id":"0","licno":"","fk_i_created_by":"8","dt_created_at":"2021-09-29 09:09:02","fk_i_dept_id":"7","customer_name":"حنان فؤاد شفيق سقف الحيط ","s_attach1":"","s_attach2":"","connected_to":"0","ReciptNo":null,"AmountInNIS":null,"json_fees":"{\"\\u0631\\u0633\\u0648\\u0645 \\u0627\\u0644\\u0625\\u0634\\u062a\\u0631\\u0627\\u0643\":\"1500\",\"\\u0631\\u0633\\u0648\\u0645 \\u062a\\u0642\\u062f\\u064a\\u0645 \\u0637\\u0644\\u0628\":\"70\",\"\\u062b\\u0645\\u0646 \\u0627\\u0644\\u0639\\u062f\\u0627\\u062f\":\"550\",\"\\u062b\\u0645\\u0646 \\u0645\\u0631\\u0627\\u0628\\u0637\":\"0\",\"\\u0644\\u0648\\u0627\\u0632\\u0645 \\u062a\\u0645\\u062f\\u064a\\u062f\":\"0\",\"\\u0631\\u0633\\u0648\\u0645 \\u0645\\u0633\\u0627\\u0647\\u0645\\u0629 \\u0627\\u0644\\u0641\\u0627\\u0632 \\u0627\\u0644\\u0648\\u0627\\u062d\\u062f \\u064432 \\u0627\\u0645\\u0628\\u064a\\u0631\":\"1056\"}","owner_name":""},
{"pk_i_id":"5","capacity":"1","ampere":"32","customer_type":"8","fk_i_customer_id":"850","s_mobile":"0595273647","BusinessName":"","AddressDetailsAR":"المزل الجديد قيد الانشاء في منطقة الحبايل","d_lat":"0","d_lng":"0","ownership_type":"1","owner_type":"i","owner_id":"0","licno":"","fk_i_created_by":"7","dt_created_at":"2021-10-07 11:14:37","fk_i_dept_id":"7","customer_name":"شريف عبد الله شريف صالح","s_attach1":"","s_attach2":"","connected_to":"0","ReciptNo":null,"AmountInNIS":null,"json_fees":"{\"\\u0631\\u0633\\u0648\\u0645 \\u0627\\u0644\\u0625\\u0634\\u062a\\u0631\\u0627\\u0643\":\"0\",\"\\u0631\\u0633\\u0648\\u0645 \\u062a\\u0642\\u062f\\u064a\\u0645 \\u0637\\u0644\\u0628\":\"0\",\"\\u062b\\u0645\\u0646 \\u0627\\u0644\\u0639\\u062f\\u0627\\u062f\":\"0\",\"\\u062b\\u0645\\u0646 \\u0645\\u0631\\u0627\\u0628\\u0637\":\"0\",\"\\u0644\\u0648\\u0627\\u0632\\u0645 \\u062a\\u0645\\u062f\\u064a\\u062f\":\"0\",\"\\u0627\\u062c\\u0631\\u0629 \\u0641\\u0646\\u064a \\u0627\\u0644\\u0643\\u0647\\u0631\\u0628\\u0627\\u0621\":\"0\",\"\\u0645\\u0628\\u0644\\u063a \\u0645\\u0633\\u0627\\u0647\\u0645\\u0629 \\u0627\\u0644\\u0645\\u0634\\u062a\\u0631\\u0643\":\"0\"}","owner_name":""},
{"pk_i_id":"6","capacity":"0","ampere":"0","customer_type":"i","fk_i_customer_id":"596","s_mobile":"0595253250","BusinessName":"تستس","AddressDetailsAR":"   تست","d_lat":"0","d_lng":"0","ownership_type":"1","owner_type":"5","owner_id":"96","licno":"","fk_i_created_by":"6","dt_created_at":"2021-10-09 18:50:38","fk_i_dept_id":"8","customer_name":"هاني العمري ","s_attach1":"","s_attach2":"","connected_to":"0","ReciptNo":null,"AmountInNIS":null,"json_fees":"{\"\\u0631\\u0633\\u0648\\u0645 \\u0627\\u0644\\u0627\\u0634\\u062a\\u0631\\u0627\\u0643\":\"800\",\"\\u062b\\u0645\\u0646 \\u0627\\u0644\\u0639\\u062f\\u0627\\u062f\":\"150\",\"\\u062c\\u062f\\u064a\\u062f\":\"122\"}","owner_name":""},
{"pk_i_id":"7","capacity":"0","ampere":"0","customer_type":"i","fk_i_customer_id":"596","s_mobile":"0595253250","BusinessName":"","AddressDetailsAR":"   الحارة الجديدة","d_lat":"0","d_lng":"0","ownership_type":"1","owner_type":"5","owner_id":"96","licno":"33333","fk_i_created_by":"6","dt_created_at":"2021-10-09 19:07:17","fk_i_dept_id":"8","customer_name":"هاني العمري ","s_attach1":"","s_attach2":"","connected_to":"0","ReciptNo":null,"AmountInNIS":null,"json_fees":"{\"\\u0631\\u0633\\u0648\\u0645 \\u0627\\u0644\\u0627\\u0634\\u062a\\u0631\\u0627\\u0643\":\"800\",\"\\u062b\\u0645\\u0646 \\u0627\\u0644\\u0639\\u062f\\u0627\\u062f\":\"150\"}","owner_name":""},
{"pk_i_id":"8","capacity":"0","ampere":"0","customer_type":"i","fk_i_customer_id":"850","s_mobile":"0595273647","BusinessName":"","AddressDetailsAR":"الحارة الفوقا   ","d_lat":"0","d_lng":"0","ownership_type":"1","owner_type":"8","owner_id":"50","licno":"","fk_i_created_by":"7","dt_created_at":"2021-10-09 22:15:37","fk_i_dept_id":"8","customer_name":"شريف عبد الله شريف صالح","s_attach1":"","s_attach2":"","connected_to":"0","ReciptNo":null,"AmountInNIS":null,"json_fees":"{\"\\u0631\\u0633\\u0648\\u0645 \\u0627\\u0644\\u0627\\u0634\\u062a\\u0631\\u0627\\u0643\":\"0\",\"\\u062b\\u0645\\u0646 \\u0627\\u0644\\u0639\\u062f\\u0627\\u062f\":\"0\"}","owner_name":""},
{"pk_i_id":"9","capacity":"0","ampere":"0","customer_type":"i","fk_i_customer_id":"850","s_mobile":"0595273647","BusinessName":"","AddressDetailsAR":"المنزل الجديد قيد الانشاء في منطقة الحبايل \/ السحيلة","d_lat":"0","d_lng":"0","ownership_type":"1","owner_type":"8","owner_id":"50","licno":"3342\/5\/2021","fk_i_created_by":"7","dt_created_at":"2021-10-10 14:36:59","fk_i_dept_id":"8","customer_name":"شريف عبد الله شريف صالح","s_attach1":"","s_attach2":"","connected_to":"0","ReciptNo":null,"AmountInNIS":null,"json_fees":"{\"\\u0631\\u0633\\u0648\\u0645 \\u0627\\u0644\\u0627\\u0634\\u062a\\u0631\\u0627\\u0643\":\"0\",\"\\u062b\\u0645\\u0646 \\u0627\\u0644\\u0639\\u062f\\u0627\\u062f\":\"0\",\"\\u062b\\u0645\\u0646 \\u0645\\u0648\\u0627\\u062f \\u062a\\u0645\\u062f\\u064a\\u062f\\u0627\\u062a\":\"0\"}","owner_name":""},
{"pk_i_id":"10","capacity":"1","ampere":"32","customer_type":"8","fk_i_customer_id":"857","s_mobile":"0569056186","BusinessName":"","AddressDetailsAR":"البصة والخنادق \/ منزل والدة الطابق الثالث  ","d_lat":"0","d_lng":"0","ownership_type":"1","owner_type":"i","owner_id":"0","licno":"","fk_i_created_by":"7","dt_created_at":"2021-10-12 10:48:24","fk_i_dept_id":"7","customer_name":"عبد الله احمد محمد صالح","s_attach1":"","s_attach2":"","connected_to":"0","ReciptNo":null,"AmountInNIS":null,"json_fees":"{\"\\u0631\\u0633\\u0648\\u0645 \\u0627\\u0644\\u0625\\u0634\\u062a\\u0631\\u0627\\u0643\":\"0\",\"\\u0631\\u0633\\u0648\\u0645 \\u062a\\u0642\\u062f\\u064a\\u0645 \\u0637\\u0644\\u0628\":\"0\",\"\\u062b\\u0645\\u0646 \\u0627\\u0644\\u0639\\u062f\\u0627\\u062f\":\"0\",\"\\u062b\\u0645\\u0646 \\u0645\\u0631\\u0627\\u0628\\u0637\":\"0\",\"\\u0644\\u0648\\u0627\\u0632\\u0645 \\u062a\\u0645\\u062f\\u064a\\u062f\":\"0\",\"\\u0627\\u062c\\u0631\\u0629 \\u0641\\u0646\\u064a \\u0627\\u0644\\u0643\\u0647\\u0631\\u0628\\u0627\\u0621\":\"\"}","owner_name":""},
{"pk_i_id":"11","capacity":"1","ampere":"32","customer_type":"2","fk_i_customer_id":"271","s_mobile":"0568994689","BusinessName":"","AddressDetailsAR":"منزل قيد الانشاء منطقة مغارة صبحة","d_lat":"0","d_lng":"0","ownership_type":"1","owner_type":"i","owner_id":"0","licno":"","fk_i_created_by":"7","dt_created_at":"2021-10-16 15:24:22","fk_i_dept_id":"7","customer_name":"يحيى سليمان عبد القادر صالح","s_attach1":"","s_attach2":"","connected_to":"0","ReciptNo":null,"AmountInNIS":null,"json_fees":"{\"\\u0631\\u0633\\u0648\\u0645 \\u0627\\u0644\\u0625\\u0634\\u062a\\u0631\\u0627\\u0643\":\"1600\",\"\\u0631\\u0633\\u0648\\u0645 \\u062a\\u0642\\u062f\\u064a\\u0645 \\u0637\\u0644\\u0628\":\"0\",\"\\u062b\\u0645\\u0646 \\u0627\\u0644\\u0639\\u062f\\u0627\\u062f\":\"0\",\"\\u062b\\u0645\\u0646 \\u0645\\u0631\\u0627\\u0628\\u0637\":\"0\",\"\\u0644\\u0648\\u0627\\u0632\\u0645 \\u062a\\u0645\\u062f\\u064a\\u062f\":\"0\"}","owner_name":""},
{"pk_i_id":"12","capacity":"0","ampere":"0","customer_type":"i","fk_i_customer_id":"271","s_mobile":"0568994689","BusinessName":"","AddressDetailsAR":"منزل قيد الانشاء \/ منطقة مغارة صبحة","d_lat":"0","d_lng":"0","ownership_type":"1","owner_type":"2","owner_id":"71","licno":"","fk_i_created_by":"7","dt_created_at":"2021-10-16 15:25:34","fk_i_dept_id":"8","customer_name":"يحيى سليمان عبد القادر صالح","s_attach1":"","s_attach2":"","connected_to":"0","ReciptNo":null,"AmountInNIS":null,"json_fees":"{\"\\u0631\\u0633\\u0648\\u0645 \\u0627\\u0644\\u0627\\u0634\\u062a\\u0631\\u0627\\u0643\":\"800\",\"\\u062b\\u0645\\u0646 \\u0627\\u0644\\u0639\\u062f\\u0627\\u062f\":\"0\"}","owner_name":""},
{"pk_i_id":"13","capacity":"1","ampere":"32","customer_type":"5","fk_i_customer_id":"579","s_mobile":"0568150167","BusinessName":"","AddressDetailsAR":"وسط البلد \/ قرب المسجد \/ منزل قيد الانشاء ","d_lat":"0","d_lng":"0","ownership_type":"1","owner_type":"i","owner_id":"0","licno":"","fk_i_created_by":"7","dt_created_at":"2021-10-30 13:44:20","fk_i_dept_id":"7","customer_name":"همام حسني شريف صالح","s_attach1":"","s_attach2":"","connected_to":"0","ReciptNo":null,"AmountInNIS":null,"json_fees":"{\"\\u0631\\u0633\\u0648\\u0645 \\u0627\\u0644\\u0625\\u0634\\u062a\\u0631\\u0627\\u0643\":\"1600\",\"\\u0631\\u0633\\u0648\\u0645 \\u062a\\u0642\\u062f\\u064a\\u0645 \\u0637\\u0644\\u0628\":\"0\",\"\\u062b\\u0645\\u0646 \\u0627\\u0644\\u0639\\u062f\\u0627\\u062f\":\"0\",\"\\u062b\\u0645\\u0646 \\u0645\\u0631\\u0627\\u0628\\u0637\":\"0\",\"\\u0644\\u0648\\u0627\\u0632\\u0645 \\u062a\\u0645\\u062f\\u064a\\u062f\":\"0\",\"\\u0627\\u062c\\u0631\\u0629 \\u0641\\u0646\\u064a \\u0627\\u0644\\u0643\\u0647\\u0631\\u0628\\u0627\\u0621\":\"\"}","owner_name":""},
{"pk_i_id":"14","capacity":"1","ampere":"32","customer_type":"2","fk_i_customer_id":"27","s_mobile":"0598531943","BusinessName":"","AddressDetailsAR":"الحارة الفوقا \/ استراك فرعي في منزلي الطابق الثاني","d_lat":"0","d_lng":"0","ownership_type":"1","owner_type":"i","owner_id":"0","licno":"","fk_i_created_by":"7","dt_created_at":"2021-11-04 09:11:28","fk_i_dept_id":"7","customer_name":"علي محمد فائق صالح","s_attach1":"","s_attach2":"","connected_to":"0","ReciptNo":null,"AmountInNIS":null,"json_fees":"{\"\\u0631\\u0633\\u0648\\u0645 \\u0627\\u0644\\u0625\\u0634\\u062a\\u0631\\u0627\\u0643\":\"800\",\"\\u0631\\u0633\\u0648\\u0645 \\u062a\\u0642\\u062f\\u064a\\u0645 \\u0637\\u0644\\u0628\":\"\",\"\\u062b\\u0645\\u0646 \\u0627\\u0644\\u0639\\u062f\\u0627\\u062f\":\"\",\"\\u062b\\u0645\\u0646 \\u0645\\u0631\\u0627\\u0628\\u0637\":\"\",\"\\u0644\\u0648\\u0627\\u0632\\u0645 \\u062a\\u0645\\u062f\\u064a\\u062f\":\"0\"}","owner_name":""},
{"pk_i_id":"15","capacity":"0","ampere":"0","customer_type":"i","fk_i_customer_id":"16","s_mobile":"0598180500","BusinessName":"","AddressDetailsAR":"الحارة الفوقا \/ الطابق الاول من منزل والدي  ","d_lat":"0","d_lng":"0","ownership_type":"1","owner_type":"1","owner_id":"6","licno":"","fk_i_created_by":"7","dt_created_at":"2021-11-06 09:46:04","fk_i_dept_id":"8","customer_name":"احمد فواز احمد صالح","s_attach1":"","s_attach2":"","connected_to":"0","ReciptNo":null,"AmountInNIS":null,"json_fees":"{\"\\u0631\\u0633\\u0648\\u0645 \\u0627\\u0644\\u0627\\u0634\\u062a\\u0631\\u0627\\u0643\":\"800\",\"\\u062b\\u0645\\u0646 \\u0627\\u0644\\u0639\\u062f\\u0627\\u062f\":\"0\"}","owner_name":""},
{"pk_i_id":"16","capacity":"0","ampere":"0","customer_type":"i","fk_i_customer_id":"17","s_mobile":"0568093323","BusinessName":"","AddressDetailsAR":"الحارة الفوقا  \/ الطابق الثالث من منزل والدي","d_lat":"0","d_lng":"0","ownership_type":"1","owner_type":"1","owner_id":"7","licno":"","fk_i_created_by":"7","dt_created_at":"2021-11-06 09:47:58","fk_i_dept_id":"8","customer_name":"محمد فواز احمد صالح","s_attach1":"","s_attach2":"","connected_to":"0","ReciptNo":null,"AmountInNIS":null,"json_fees":"{\"\\u0631\\u0633\\u0648\\u0645 \\u0627\\u0644\\u0627\\u0634\\u062a\\u0631\\u0627\\u0643\":\"800\",\"\\u062b\\u0645\\u0646 \\u0627\\u0644\\u0639\\u062f\\u0627\\u062f\":\"0\"}","owner_name":""},
{"pk_i_id":"17","capacity":"0","ampere":"0","customer_type":"i","fk_i_customer_id":"583","s_mobile":"0597478043","BusinessName":"","AddressDetailsAR":"الشارع الرئيسي \/ منلي مدخل القرية مقابل المعصرة  ","d_lat":"0","d_lng":"0","ownership_type":"1","owner_type":"5","owner_id":"83","licno":"","fk_i_created_by":"7","dt_created_at":"2021-11-06 12:19:03","fk_i_dept_id":"8","customer_name":"عمر عيسى سليمان مخلوف","s_attach1":"","s_attach2":"","connected_to":"0","ReciptNo":null,"AmountInNIS":null,"json_fees":"{\"\\u0631\\u0633\\u0648\\u0645 \\u0627\\u0644\\u0627\\u0634\\u062a\\u0631\\u0627\\u0643\":\"400\",\"\\u062b\\u0645\\u0646 \\u0627\\u0644\\u0639\\u062f\\u0627\\u062f\":\"0\"}","owner_name":""},
{"pk_i_id":"18","capacity":"0","ampere":"0","customer_type":"i","fk_i_customer_id":"889","s_mobile":"0599350992","BusinessName":"","AddressDetailsAR":"   منطقة الهيش - تل \/ سلمة الحج صالح","d_lat":"0","d_lng":"0","ownership_type":"1","owner_type":"8","owner_id":"89","licno":"","fk_i_created_by":"7","dt_created_at":"2021-11-09 13:03:30","fk_i_dept_id":"8","customer_name":"ابراهيم علي صالح شتية","s_attach1":"","s_attach2":"","connected_to":"0","ReciptNo":null,"AmountInNIS":null,"json_fees":"{\"\\u0631\\u0633\\u0648\\u0645 \\u0627\\u0644\\u0627\\u0634\\u062a\\u0631\\u0627\\u0643\":\"800\",\"\\u062b\\u0645\\u0646 \\u0627\\u0644\\u0639\\u062f\\u0627\\u062f\":\"0\"}","owner_name":""},
{"pk_i_id":"19","capacity":"1","ampere":"32","customer_type":"2","fk_i_customer_id":"26","s_mobile":"0599134453","BusinessName":"","AddressDetailsAR":"الحومة \/ الطابق الثالث  \/فرعي","d_lat":"0","d_lng":"0","ownership_type":"1","owner_type":"i","owner_id":"0","licno":"","fk_i_created_by":"7","dt_created_at":"2021-11-13 09:19:57","fk_i_dept_id":"7","customer_name":"وليد يوسف عبد القادر عصايرة","s_attach1":"","s_attach2":"","connected_to":"0","ReciptNo":null,"AmountInNIS":null,"json_fees":"{\"\\u0631\\u0633\\u0648\\u0645 \\u0627\\u0644\\u0625\\u0634\\u062a\\u0631\\u0627\\u0643\":\"800\",\"\\u0631\\u0633\\u0648\\u0645 \\u062a\\u0642\\u062f\\u064a\\u0645 \\u0637\\u0644\\u0628\":\"\",\"\\u062b\\u0645\\u0646 \\u0627\\u0644\\u0639\\u062f\\u0627\\u062f\":\"\",\"\\u062b\\u0645\\u0646 \\u0645\\u0631\\u0627\\u0628\\u0637\":\"\",\"\\u0644\\u0648\\u0627\\u0632\\u0645 \\u062a\\u0645\\u062f\\u064a\\u062f\":\"0\"}","owner_name":""},
{"pk_i_id":"20","capacity":"1","ampere":"32","customer_type":"4","fk_i_customer_id":"411","s_mobile":"0598931656","BusinessName":"","AddressDetailsAR":"المنطقة الشرقية الحبايل \/ منزل قيد الانشاء","d_lat":"0","d_lng":"0","ownership_type":"1","owner_type":"i","owner_id":"0","licno":"","fk_i_created_by":"7","dt_created_at":"2021-11-16 10:48:10","fk_i_dept_id":"7","customer_name":"عماد جبر جبريل صالح","s_attach1":"","s_attach2":"","connected_to":"0","ReciptNo":null,"AmountInNIS":null,"json_fees":"{\"\\u0631\\u0633\\u0648\\u0645 \\u0627\\u0644\\u0625\\u0634\\u062a\\u0631\\u0627\\u0643\":\"\",\"\\u0631\\u0633\\u0648\\u0645 \\u062a\\u0642\\u062f\\u064a\\u0645 \\u0637\\u0644\\u0628\":\"\",\"\\u062b\\u0645\\u0646 \\u0627\\u0644\\u0639\\u062f\\u0627\\u062f\":\"\",\"\\u062b\\u0645\\u0646 \\u0645\\u0631\\u0627\\u0628\\u0637\":\"\",\"\\u0644\\u0648\\u0627\\u0632\\u0645 \\u062a\\u0645\\u062f\\u064a\\u062f\":\"0\"}","owner_name":""},
{"pk_i_id":"21","capacity":"0","ampere":"0","customer_type":"i","fk_i_customer_id":"411","s_mobile":"0598931656","BusinessName":"","AddressDetailsAR":"المنطقة الشرقية - الحبايل \/ منزل قيد الانشاء","d_lat":"0","d_lng":"0","ownership_type":"1","owner_type":"4","owner_id":"11","licno":"","fk_i_created_by":"7","dt_created_at":"2021-11-16 10:52:04","fk_i_dept_id":"8","customer_name":"عماد جبر جبريل صالح","s_attach1":"","s_attach2":"","connected_to":"0","ReciptNo":null,"AmountInNIS":null,"json_fees":"{\"\\u0631\\u0633\\u0648\\u0645 \\u0627\\u0644\\u0627\\u0634\\u062a\\u0631\\u0627\\u0643\":\"\",\"\\u062b\\u0645\\u0646 \\u0627\\u0644\\u0639\\u062f\\u0627\\u062f\":\"\"}","owner_name":""},
{"pk_i_id":"22","capacity":"1","ampere":"32","customer_type":"8","fk_i_customer_id":"891","s_mobile":"0568946667","BusinessName":"","AddressDetailsAR":"الكرايم \/ حبايل عامر ","d_lat":"0","d_lng":"0","ownership_type":"1","owner_type":"i","owner_id":"0","licno":"","fk_i_created_by":"7","dt_created_at":"2021-11-18 13:53:25","fk_i_dept_id":"7","customer_name":"ليث محمد عيسى عصايرة","s_attach1":"","s_attach2":"","connected_to":"0","ReciptNo":null,"AmountInNIS":null,"json_fees":"{\"\\u0631\\u0633\\u0648\\u0645 \\u0627\\u0644\\u0625\\u0634\\u062a\\u0631\\u0627\\u0643\":\"1600\",\"\\u0631\\u0633\\u0648\\u0645 \\u062a\\u0642\\u062f\\u064a\\u0645 \\u0637\\u0644\\u0628\":\"0\",\"\\u062b\\u0645\\u0646 \\u0627\\u0644\\u0639\\u062f\\u0627\\u062f\":\"0\",\"\\u062b\\u0645\\u0646 \\u0645\\u0631\\u0627\\u0628\\u0637\":\"0\",\"\\u0644\\u0648\\u0627\\u0632\\u0645 \\u062a\\u0645\\u062f\\u064a\\u062f\":\"0\"}","owner_name":""},
{"pk_i_id":"23","capacity":"0","ampere":"0","customer_type":"i","fk_i_customer_id":"891","s_mobile":"0568946667","BusinessName":"","AddressDetailsAR":"الكرايم    \/ حبايل عامر منزل قيد الانشاء","d_lat":"0","d_lng":"0","ownership_type":"1","owner_type":"8","owner_id":"91","licno":"","fk_i_created_by":"7","dt_created_at":"2021-11-18 13:55:42","fk_i_dept_id":"8","customer_name":"ليث محمد عيسى عصايرة","s_attach1":"","s_attach2":"","connected_to":"0","ReciptNo":null,"AmountInNIS":null,"json_fees":"{\"\\u0631\\u0633\\u0648\\u0645 \\u0627\\u0644\\u0627\\u0634\\u062a\\u0631\\u0627\\u0643\":\"1600\",\"\\u062b\\u0645\\u0646 \\u0627\\u0644\\u0639\\u062f\\u0627\\u062f\":\"0\"}","owner_name":""},
{"pk_i_id":"24","capacity":"1","ampere":"32","customer_type":"8","fk_i_customer_id":"892","s_mobile":"0594184724","BusinessName":"","AddressDetailsAR":"طريق فقاس \/ منزل قيد الانشاء","d_lat":"0","d_lng":"0","ownership_type":"1","owner_type":"i","owner_id":"0","licno":"","fk_i_created_by":"7","dt_created_at":"2021-11-22 13:26:05","fk_i_dept_id":"7","customer_name":"احمد محمد عيسى صالح","s_attach1":"","s_attach2":"","connected_to":"0","ReciptNo":null,"AmountInNIS":null,"json_fees":"{\"\\u0631\\u0633\\u0648\\u0645 \\u0627\\u0644\\u0625\\u0634\\u062a\\u0631\\u0627\\u0643\":\"1600\",\"\\u0631\\u0633\\u0648\\u0645 \\u062a\\u0642\\u062f\\u064a\\u0645 \\u0637\\u0644\\u0628\":\"\",\"\\u062b\\u0645\\u0646 \\u0627\\u0644\\u0639\\u062f\\u0627\\u062f\":\"\",\"\\u062b\\u0645\\u0646 \\u0645\\u0631\\u0627\\u0628\\u0637\":\"\",\"\\u0644\\u0648\\u0627\\u0632\\u0645 \\u062a\\u0645\\u062f\\u064a\\u062f\":\"0\"}","owner_name":""},
{"pk_i_id":"25","capacity":"1","ampere":"32","customer_type":"8","fk_i_customer_id":"893","s_mobile":"0598229501","BusinessName":"","AddressDetailsAR":"عماير والشعب \/ جنوب كسارة ابناء محمود داود \/ منزل قيد الانشاء","d_lat":"0","d_lng":"0","ownership_type":"1","owner_type":"i","owner_id":"0","licno":"3492\/8\/2019","fk_i_created_by":"7","dt_created_at":"2021-11-27 11:56:48","fk_i_dept_id":"7","customer_name":"مؤيد محمد موسى عصايرة","s_attach1":"","s_attach2":"","connected_to":"0","ReciptNo":null,"AmountInNIS":null,"json_fees":"{\"\\u0631\\u0633\\u0648\\u0645 \\u0627\\u0644\\u0625\\u0634\\u062a\\u0631\\u0627\\u0643\":\"1600\",\"\\u0631\\u0633\\u0648\\u0645 \\u062a\\u0642\\u062f\\u064a\\u0645 \\u0637\\u0644\\u0628\":\"0\",\"\\u062b\\u0645\\u0646 \\u0627\\u0644\\u0639\\u062f\\u0627\\u062f\":\"0\",\"\\u062b\\u0645\\u0646 \\u0645\\u0631\\u0627\\u0628\\u0637\":\"0\",\"\\u0644\\u0648\\u0627\\u0632\\u0645 \\u062a\\u0645\\u062f\\u064a\\u062f\":\"0\"}","owner_name":""},
{"pk_i_id":"26","capacity":"1","ampere":"32","customer_type":"8","fk_i_customer_id":"895","s_mobile":"0568374862","BusinessName":"","AddressDetailsAR":"الحارة الفوقا  \/ الطابق الثاني من منزل اخيه يزيد احمد حمدان ","d_lat":"0","d_lng":"0","ownership_type":"1","owner_type":"i","owner_id":"0","licno":"","fk_i_created_by":"7","dt_created_at":"2021-11-27 12:45:40","fk_i_dept_id":"7","customer_name":"محمد احمد محمد حمدان","s_attach1":"","s_attach2":"","connected_to":"0","ReciptNo":null,"AmountInNIS":null,"json_fees":"{\"\\u0631\\u0633\\u0648\\u0645 \\u0627\\u0644\\u0625\\u0634\\u062a\\u0631\\u0627\\u0643\":\"800\",\"\\u0631\\u0633\\u0648\\u0645 \\u062a\\u0642\\u062f\\u064a\\u0645 \\u0637\\u0644\\u0628\":\"0\",\"\\u062b\\u0645\\u0646 \\u0627\\u0644\\u0639\\u062f\\u0627\\u062f\":\"0\",\"\\u062b\\u0645\\u0646 \\u0645\\u0631\\u0627\\u0628\\u0637\":\"0\",\"\\u0644\\u0648\\u0627\\u0632\\u0645 \\u062a\\u0645\\u062f\\u064a\\u062f\":\"0\"}","owner_name":""},
{"pk_i_id":"27","capacity":"1","ampere":"32","customer_type":"8","fk_i_customer_id":"899","s_mobile":"0597702251","BusinessName":"","AddressDetailsAR":"حبايل عامر \/ بجانب منزل حسن بسام \/ منزل قيد الانشاء   ","d_lat":"0","d_lng":"0","ownership_type":"1","owner_type":"i","owner_id":"0","licno":"3666\/9\/2021","fk_i_created_by":"7","dt_created_at":"2021-12-05 12:40:14","fk_i_dept_id":"7","customer_name":"حبيب روحي عبد الكريم عصايرة","s_attach1":"","s_attach2":"","connected_to":"0","ReciptNo":null,"AmountInNIS":null,"json_fees":"{\"\\u0631\\u0633\\u0648\\u0645 \\u0627\\u0644\\u0625\\u0634\\u062a\\u0631\\u0627\\u0643\":\"\",\"\\u0631\\u0633\\u0648\\u0645 \\u062a\\u0642\\u062f\\u064a\\u0645 \\u0637\\u0644\\u0628\":\"\",\"\\u062b\\u0645\\u0646 \\u0627\\u0644\\u0639\\u062f\\u0627\\u062f\":\"\",\"\\u062b\\u0645\\u0646 \\u0645\\u0631\\u0627\\u0628\\u0637\":\"\",\"\\u0644\\u0648\\u0627\\u0632\\u0645 \\u062a\\u0645\\u062f\\u064a\\u062f\":\"0\"}","owner_name":""},
{"pk_i_id":"28","capacity":"0","ampere":"0","customer_type":"i","fk_i_customer_id":"899","s_mobile":"0597702251","BusinessName":"","AddressDetailsAR":"حبايل عامر \/ بجانب منزل حسن بسام \/ منزل قيد الانشاء","d_lat":"0","d_lng":"0","ownership_type":"1","owner_type":"8","owner_id":"99","licno":"3666\/9\/2021","fk_i_created_by":"7","dt_created_at":"2021-12-05 12:42:30","fk_i_dept_id":"8","customer_name":"حبيب روحي عبد الكريم عصايرة","s_attach1":"","s_attach2":"","connected_to":"0","ReciptNo":null,"AmountInNIS":null,"json_fees":"{\"\\u0631\\u0633\\u0648\\u0645 \\u0627\\u0644\\u0627\\u0634\\u062a\\u0631\\u0627\\u0643\":\"\",\"\\u062b\\u0645\\u0646 \\u0627\\u0644\\u0639\\u062f\\u0627\\u062f\":\"\"}","owner_name":""},
{"pk_i_id":"29","capacity":"0","ampere":"0","customer_type":"i","fk_i_customer_id":"313","s_mobile":"0598558392","BusinessName":"","AddressDetailsAR":" فقاس    ","d_lat":"0","d_lng":"0","ownership_type":"1","owner_type":"3","owner_id":"13","licno":"","fk_i_created_by":"7","dt_created_at":"2021-12-12 11:11:06","fk_i_dept_id":"8","customer_name":"داوود محمود داود صالح","s_attach1":"","s_attach2":"","connected_to":"0","ReciptNo":null,"AmountInNIS":null,"json_fees":"{\"\\u0631\\u0633\\u0648\\u0645 \\u0627\\u0644\\u0627\\u0634\\u062a\\u0631\\u0627\\u0643\":\"800\",\"\\u062b\\u0645\\u0646 \\u0627\\u0644\\u0639\\u062f\\u0627\\u062f\":\"\"}","owner_name":""},
{"pk_i_id":"30","capacity":"2","ampere":"32","customer_type":"3","fk_i_customer_id":"313","s_mobile":"0598558392","BusinessName":"","AddressDetailsAR":"الراس ","d_lat":"0","d_lng":"0","ownership_type":"1","owner_type":"i","owner_id":"0","licno":"","fk_i_created_by":"7","dt_created_at":"2021-12-12 11:18:34","fk_i_dept_id":"7","customer_name":"داوود محمود داود صالح","s_attach1":"","s_attach2":"","connected_to":"0","ReciptNo":null,"AmountInNIS":null,"json_fees":"{\"\\u0631\\u0633\\u0648\\u0645 \\u0627\\u0644\\u0625\\u0634\\u062a\\u0631\\u0627\\u0643 (250 \\u0634 \\u0644\\u0644\\u0623\\u0645\\u0628\\u064a\\u0631)\":\"3720\",\"\\u062b\\u0645\\u0646 \\u0627\\u0644\\u0639\\u062f\\u0627\\u062f\":\"\",\"\\u0631\\u0633\\u0648\\u0645 \\u062a\\u0642\\u062f\\u064a\\u0645 \\u0637\\u0644\\u0628\":\"\",\"\\u062b\\u0645\\u0646 \\u0645\\u0631\\u0627\\u0628\\u0637\":\"\",\"\\u062b\\u0645\\u0646 \\u0645\\u0648\\u0627\\u062f\":\"0\"}","owner_name":""},
{"pk_i_id":"31","capacity":"1","ampere":"32","customer_type":"4","fk_i_customer_id":"439","s_mobile":"0598100996","BusinessName":"","AddressDetailsAR":"الراس \/ منزل قيد الانشاء","d_lat":"0","d_lng":"0","ownership_type":"1","owner_type":"i","owner_id":"0","licno":"لا يوجد","fk_i_created_by":"7","dt_created_at":"2022-01-17 09:48:29","fk_i_dept_id":"7","customer_name":"باسل يوسف داود صالح","s_attach1":"","s_attach2":"","connected_to":"0","ReciptNo":null,"AmountInNIS":null,"json_fees":"{\"\\u0631\\u0633\\u0648\\u0645 \\u0627\\u0644\\u0625\\u0634\\u062a\\u0631\\u0627\\u0643\":\"1600\",\"\\u0631\\u0633\\u0648\\u0645 \\u062a\\u0642\\u062f\\u064a\\u0645 \\u0637\\u0644\\u0628\":\"\",\"\\u062b\\u0645\\u0646 \\u0627\\u0644\\u0639\\u062f\\u0627\\u062f\":\"\",\"\\u062b\\u0645\\u0646 \\u0645\\u0631\\u0627\\u0628\\u0637\":\"\",\"\\u0644\\u0648\\u0627\\u0632\\u0645 \\u062a\\u0645\\u062f\\u064a\\u062f\":\"0\",\"\\u0645\\u0633\\u0627\\u0647\\u0645\\u0629 \\u062e\\u0637 \\u0627\\u0644\\u0643\\u0647\\u0631\\u0628\\u0627\\u0621\":\"1000\"}","owner_name":""},
{"pk_i_id":"32","capacity":"0","ampere":"0","customer_type":"i","fk_i_customer_id":"439","s_mobile":"0598100996","BusinessName":"","AddressDetailsAR":"الراس  \/ منزل قيد الانشاء","d_lat":"0","d_lng":"0","ownership_type":"1","owner_type":"4","owner_id":"39","licno":"لا يوجد","fk_i_created_by":"7","dt_created_at":"2022-01-17 09:52:03","fk_i_dept_id":"8","customer_name":"باسل يوسف داود صالح","s_attach1":"","s_attach2":"","connected_to":"0","ReciptNo":null,"AmountInNIS":null,"json_fees":"{\"\\u0631\\u0633\\u0648\\u0645 \\u0627\\u0644\\u0627\\u0634\\u062a\\u0631\\u0627\\u0643\":\"800\",\"\\u062b\\u0645\\u0646 \\u0627\\u0644\\u0639\\u062f\\u0627\\u062f\":\"\"}","owner_name":""},
{"pk_i_id":"33","capacity":"1","ampere":"32","customer_type":"9","fk_i_customer_id":"921","s_mobile":"0568279161","BusinessName":"","AddressDetailsAR":"وسط البلد   ","d_lat":"0","d_lng":"0","ownership_type":"1","owner_type":"i","owner_id":"0","licno":"","fk_i_created_by":"8","dt_created_at":"2022-02-05 09:12:30","fk_i_dept_id":"7","customer_name":"احمد نافز عثمان حمدان","s_attach1":"","s_attach2":"","connected_to":"0","ReciptNo":null,"AmountInNIS":null,"json_fees":"{\"\\u0631\\u0633\\u0648\\u0645 \\u0627\\u0644\\u0625\\u0634\\u062a\\u0631\\u0627\\u0643\":\"800\",\"\\u0631\\u0633\\u0648\\u0645 \\u062a\\u0642\\u062f\\u064a\\u0645 \\u0637\\u0644\\u0628\":\"0\",\"\\u062b\\u0645\\u0646 \\u0627\\u0644\\u0639\\u062f\\u0627\\u062f\":\"0\",\"\\u062b\\u0645\\u0646 \\u0645\\u0631\\u0627\\u0628\\u0637\":\"0\",\"\\u0644\\u0648\\u0627\\u0632\\u0645 \\u062a\\u0645\\u062f\\u064a\\u062f\":\"0\"}","owner_name":""},
{"pk_i_id":"34","capacity":"1","ampere":"32","customer_type":"5","fk_i_customer_id":"509","s_mobile":"0568279121","BusinessName":"","AddressDetailsAR":"وسط البلد   ","d_lat":"0","d_lng":"0","ownership_type":"1","owner_type":"i","owner_id":"0","licno":"","fk_i_created_by":"7","dt_created_at":"2022-02-08 12:40:32","fk_i_dept_id":"7","customer_name":"نصر فتحي نجم عصايرة","s_attach1":"","s_attach2":"","connected_to":"0","ReciptNo":null,"AmountInNIS":null,"json_fees":"{\"\\u0631\\u0633\\u0648\\u0645 \\u0627\\u0644\\u0625\\u0634\\u062a\\u0631\\u0627\\u0643\":\"800\",\"\\u0631\\u0633\\u0648\\u0645 \\u062a\\u0642\\u062f\\u064a\\u0645 \\u0637\\u0644\\u0628\":\"\",\"\\u062b\\u0645\\u0646 \\u0627\\u0644\\u0639\\u062f\\u0627\\u062f\":\"\",\"\\u062b\\u0645\\u0646 \\u0645\\u0631\\u0627\\u0628\\u0637\":\"\",\"\\u0644\\u0648\\u0627\\u0632\\u0645 \\u062a\\u0645\\u062f\\u064a\\u062f\":\"0\"}","owner_name":""},
{"pk_i_id":"35","capacity":"1","ampere":"32","customer_type":"8","fk_i_customer_id":"83","s_mobile":"0598115450","BusinessName":"","AddressDetailsAR":"وسط البلد   وسط البلد قرب المسجد","d_lat":"0","d_lng":"0","ownership_type":"1","owner_type":"i","owner_id":"0","licno":"","fk_i_created_by":"7","dt_created_at":"2022-02-13 12:00:08","fk_i_dept_id":"7","customer_name":"معتز يوسف ابراهيم ابو زيد","s_attach1":"","s_attach2":"","connected_to":"0","ReciptNo":null,"AmountInNIS":null,"json_fees":"{\"\\u0631\\u0633\\u0648\\u0645 \\u0627\\u0644\\u0625\\u0634\\u062a\\u0631\\u0627\\u0643\":\"800\",\"\\u0631\\u0633\\u0648\\u0645 \\u062a\\u0642\\u062f\\u064a\\u0645 \\u0637\\u0644\\u0628\":\"\",\"\\u062b\\u0645\\u0646 \\u0627\\u0644\\u0639\\u062f\\u0627\\u062f\":\"\",\"\\u062b\\u0645\\u0646 \\u0645\\u0631\\u0627\\u0628\\u0637\":\"\",\"\\u0644\\u0648\\u0627\\u0632\\u0645 \\u062a\\u0645\\u062f\\u064a\\u062f\":\"0\"}","owner_name":""},
{"pk_i_id":"36","capacity":"0","ampere":"0","customer_type":"i","fk_i_customer_id":"83","s_mobile":"0598115450","BusinessName":"","AddressDetailsAR":"وسط البلد   وسط البلد قرب المسجد","d_lat":"0","d_lng":"0","ownership_type":"1","owner_type":"8","owner_id":"3","licno":"","fk_i_created_by":"7","dt_created_at":"2022-02-13 12:01:08","fk_i_dept_id":"8","customer_name":"معتز يوسف ابراهيم ابو زيد","s_attach1":"","s_attach2":"","connected_to":"0","ReciptNo":null,"AmountInNIS":null,"json_fees":"{\"\\u0631\\u0633\\u0648\\u0645 \\u0627\\u0644\\u0627\\u0634\\u062a\\u0631\\u0627\\u0643\":\"800\",\"\\u062b\\u0645\\u0646 \\u0627\\u0644\\u0639\\u062f\\u0627\\u062f\":\"0\"}","owner_name":""},
{"pk_i_id":"37","capacity":"1","ampere":"32","customer_type":"9","fk_i_customer_id":"925","s_mobile":"0599317005","BusinessName":"","AddressDetailsAR":"الحارة الشرقية\/ الخروب الشرقي \/ منزل قيد الانشاء   ","d_lat":"0","d_lng":"0","ownership_type":"1","owner_type":"i","owner_id":"0","licno":"","fk_i_created_by":"7","dt_created_at":"2022-02-15 09:48:25","fk_i_dept_id":"7","customer_name":"بشار فوزي احمد صالح","s_attach1":"","s_attach2":"","connected_to":"0","ReciptNo":null,"AmountInNIS":null,"json_fees":"{\"\\u0631\\u0633\\u0648\\u0645 \\u0627\\u0644\\u0625\\u0634\\u062a\\u0631\\u0627\\u0643\":\"\",\"\\u0631\\u0633\\u0648\\u0645 \\u062a\\u0642\\u062f\\u064a\\u0645 \\u0637\\u0644\\u0628\":\"\",\"\\u062b\\u0645\\u0646 \\u0627\\u0644\\u0639\\u062f\\u0627\\u062f\":\"\",\"\\u062b\\u0645\\u0646 \\u0645\\u0631\\u0627\\u0628\\u0637\":\"\",\"\\u0644\\u0648\\u0627\\u0632\\u0645 \\u062a\\u0645\\u062f\\u064a\\u062f\":\"0\"}","owner_name":""},
{"pk_i_id":"38","capacity":"0","ampere":"0","customer_type":"i","fk_i_customer_id":"925","s_mobile":"0599317005","BusinessName":"","AddressDetailsAR":"الحارة الشرقية \/ الخروب الشرقي \/ منزل قيد الانشاء  ","d_lat":"0","d_lng":"0","ownership_type":"1","owner_type":"9","owner_id":"25","licno":"","fk_i_created_by":"7","dt_created_at":"2022-02-15 09:50:09","fk_i_dept_id":"8","customer_name":"بشار فوزي احمد صالح","s_attach1":"","s_attach2":"","connected_to":"0","ReciptNo":null,"AmountInNIS":null,"json_fees":"{\"\\u0631\\u0633\\u0648\\u0645 \\u0627\\u0644\\u0627\\u0634\\u062a\\u0631\\u0627\\u0643\":\"\",\"\\u062b\\u0645\\u0646 \\u0627\\u0644\\u0639\\u062f\\u0627\\u062f\":\"\"}","owner_name":""},
{"pk_i_id":"39","capacity":"1","ampere":"32","customer_type":"3","fk_i_customer_id":"398","s_mobile":"0566989813","BusinessName":"","AddressDetailsAR":"وسط البلد   ","d_lat":"0","d_lng":"0","ownership_type":"1","owner_type":"i","owner_id":"0","licno":"","fk_i_created_by":"7","dt_created_at":"2022-02-19 09:50:20","fk_i_dept_id":"7","customer_name":"شادي راسم محمد صالح","s_attach1":"","s_attach2":"","connected_to":"0","ReciptNo":null,"AmountInNIS":null,"json_fees":"{\"\\u0631\\u0633\\u0648\\u0645 \\u0627\\u0644\\u0625\\u0634\\u062a\\u0631\\u0627\\u0643\":\"800\",\"\\u0631\\u0633\\u0648\\u0645 \\u062a\\u0642\\u062f\\u064a\\u0645 \\u0637\\u0644\\u0628\":\"0\",\"\\u062b\\u0645\\u0646 \\u0627\\u0644\\u0639\\u062f\\u0627\\u062f\":\"0\",\"\\u062b\\u0645\\u0646 \\u0645\\u0631\\u0627\\u0628\\u0637\":\"0\",\"\\u0644\\u0648\\u0627\\u0632\\u0645 \\u062a\\u0645\\u062f\\u064a\\u062f\":\"0\"}","owner_name":""},
{"pk_i_id":"40","capacity":"1","ampere":"32","customer_type":"9","fk_i_customer_id":"926","s_mobile":"0566989813","BusinessName":"","AddressDetailsAR":"وسط البلد   ","d_lat":"0","d_lng":"0","ownership_type":"1","owner_type":"i","owner_id":"0","licno":"","fk_i_created_by":"7","dt_created_at":"2022-02-19 09:50:50","fk_i_dept_id":"7","customer_name":"بسام راسم محمد صالح","s_attach1":"","s_attach2":"","connected_to":"0","ReciptNo":null,"AmountInNIS":null,"json_fees":"{\"\\u0631\\u0633\\u0648\\u0645 \\u0627\\u0644\\u0625\\u0634\\u062a\\u0631\\u0627\\u0643\":\"800\",\"\\u0631\\u0633\\u0648\\u0645 \\u062a\\u0642\\u062f\\u064a\\u0645 \\u0637\\u0644\\u0628\":\"0\",\"\\u062b\\u0645\\u0646 \\u0627\\u0644\\u0639\\u062f\\u0627\\u062f\":\"0\",\"\\u062b\\u0645\\u0646 \\u0645\\u0631\\u0627\\u0628\\u0637\":\"0\",\"\\u0644\\u0648\\u0627\\u0632\\u0645 \\u062a\\u0645\\u062f\\u064a\\u062f\":\"0\"}","owner_name":""},
{"pk_i_id":"41","capacity":"0","ampere":"0","customer_type":"i","fk_i_customer_id":"88","s_mobile":"0569848452","BusinessName":"","AddressDetailsAR":" فقاس  \/ منزل قيد الانشاء  ","d_lat":"0","d_lng":"0","ownership_type":"1","owner_type":"8","owner_id":"8","licno":"","fk_i_created_by":"7","dt_created_at":"2022-02-19 10:50:19","fk_i_dept_id":"8","customer_name":"محمود احمد محمود صالح","s_attach1":"","s_attach2":"","connected_to":"0","ReciptNo":null,"AmountInNIS":null,"json_fees":"{\"\\u0631\\u0633\\u0648\\u0645 \\u0627\\u0644\\u0627\\u0634\\u062a\\u0631\\u0627\\u0643\":\"800\",\"\\u062b\\u0645\\u0646 \\u0627\\u0644\\u0639\\u062f\\u0627\\u062f\":\"0\"}","owner_name":""},
{"pk_i_id":"42","capacity":"1","ampere":"32","customer_type":"9","fk_i_customer_id":"930","s_mobile":"0599546704","BusinessName":"","AddressDetailsAR":"الراس   \/ منزل قيد الانشاء","d_lat":"0","d_lng":"0","ownership_type":"1","owner_type":"i","owner_id":"0","licno":"","fk_i_created_by":"7","dt_created_at":"2022-02-20 12:35:04","fk_i_dept_id":"7","customer_name":"محمود غسان حسن طقاطقة","s_attach1":"","s_attach2":"","connected_to":"0","ReciptNo":null,"AmountInNIS":null,"json_fees":"{\"\\u0631\\u0633\\u0648\\u0645 \\u0627\\u0644\\u0625\\u0634\\u062a\\u0631\\u0627\\u0643\":\"1600\",\"\\u0631\\u0633\\u0648\\u0645 \\u062a\\u0642\\u062f\\u064a\\u0645 \\u0637\\u0644\\u0628\":\"0\",\"\\u062b\\u0645\\u0646 \\u0627\\u0644\\u0639\\u062f\\u0627\\u062f\":\"0\",\"\\u062b\\u0645\\u0646 \\u0645\\u0631\\u0627\\u0628\\u0637\":\"0\",\"\\u0644\\u0648\\u0627\\u0632\\u0645 \\u062a\\u0645\\u062f\\u064a\\u062f\":\"0\"}","owner_name":""},
{"pk_i_id":"43","capacity":"0","ampere":"0","customer_type":"i","fk_i_customer_id":"930","s_mobile":"0599546704","BusinessName":"","AddressDetailsAR":"الراس  \/ منزل قيد الانشاء ","d_lat":"0","d_lng":"0","ownership_type":"1","owner_type":"9","owner_id":"30","licno":"","fk_i_created_by":"7","dt_created_at":"2022-02-20 12:36:04","fk_i_dept_id":"8","customer_name":"محمود غسان حسن طقاطقة","s_attach1":"","s_attach2":"","connected_to":"0","ReciptNo":null,"AmountInNIS":null,"json_fees":"{\"\\u0631\\u0633\\u0648\\u0645 \\u0627\\u0644\\u0627\\u0634\\u062a\\u0631\\u0627\\u0643\":\"800\",\"\\u062b\\u0645\\u0646 \\u0627\\u0644\\u0639\\u062f\\u0627\\u062f\":\"0\"}","owner_name":""},
{"pk_i_id":"44","capacity":"1","ampere":"32","customer_type":"9","fk_i_customer_id":"938","s_mobile":"0597481330","BusinessName":"","AddressDetailsAR":"الشارع الرئيسي  \/ منزل قيد الانشاء \/ منطقة حبايل عامر فوق منزل سليمان ","d_lat":"0","d_lng":"0","ownership_type":"1","owner_type":"i","owner_id":"0","licno":"","fk_i_created_by":"7","dt_created_at":"2022-03-10 10:49:32","fk_i_dept_id":"7","customer_name":"وائل محمد سليمان صالح","s_attach1":"","s_attach2":"","connected_to":"0","ReciptNo":null,"AmountInNIS":null,"json_fees":"{\"\\u0631\\u0633\\u0648\\u0645 \\u0627\\u0644\\u0625\\u0634\\u062a\\u0631\\u0627\\u0643\":\"1600\",\"\\u0631\\u0633\\u0648\\u0645 \\u062a\\u0642\\u062f\\u064a\\u0645 \\u0637\\u0644\\u0628\":\"\",\"\\u062b\\u0645\\u0646 \\u0627\\u0644\\u0639\\u062f\\u0627\\u062f\":\"\",\"\\u062b\\u0645\\u0646 \\u0645\\u0631\\u0627\\u0628\\u0637\":\"\",\"\\u0644\\u0648\\u0627\\u0632\\u0645 \\u062a\\u0645\\u062f\\u064a\\u062f\":\"0\"}","owner_name":""},
{"pk_i_id":"45","capacity":"1","ampere":"32","customer_type":"9","fk_i_customer_id":"939","s_mobile":"0592599750","BusinessName":"","AddressDetailsAR":"   المنطقة الغربية ","d_lat":"0","d_lng":"0","ownership_type":"1","owner_type":"i","owner_id":"0","licno":"","fk_i_created_by":"8","dt_created_at":"2022-03-12 11:00:29","fk_i_dept_id":"7","customer_name":"صالح محمد محمود ابو خلف","s_attach1":"","s_attach2":"","connected_to":"0","ReciptNo":null,"AmountInNIS":null,"json_fees":"{\"\\u0631\\u0633\\u0648\\u0645 \\u0627\\u0644\\u0625\\u0634\\u062a\\u0631\\u0627\\u0643\":\"800\",\"\\u0631\\u0633\\u0648\\u0645 \\u062a\\u0642\\u062f\\u064a\\u0645 \\u0637\\u0644\\u0628\":\"\",\"\\u062b\\u0645\\u0646 \\u0627\\u0644\\u0639\\u062f\\u0627\\u062f\":\"\",\"\\u062b\\u0645\\u0646 \\u0645\\u0631\\u0627\\u0628\\u0637\":\"\",\"\\u0644\\u0648\\u0627\\u0632\\u0645 \\u062a\\u0645\\u062f\\u064a\\u062f\":\"0\"}","owner_name":""},
{"pk_i_id":"46","capacity":"1","ampere":"32","customer_type":"9","fk_i_customer_id":"939","s_mobile":"0592599750","BusinessName":"","AddressDetailsAR":"   المنطقة الغربية \/ منزل والده","d_lat":"0","d_lng":"0","ownership_type":"1","owner_type":"i","owner_id":"0","licno":"","fk_i_created_by":"8","dt_created_at":"2022-03-12 11:18:04","fk_i_dept_id":"7","customer_name":"صالح محمد محمود ابو خلف","s_attach1":"","s_attach2":"","connected_to":"0","ReciptNo":null,"AmountInNIS":null,"json_fees":"{\"\\u0631\\u0633\\u0648\\u0645 \\u0627\\u0644\\u0625\\u0634\\u062a\\u0631\\u0627\\u0643\":\"800\",\"\\u0631\\u0633\\u0648\\u0645 \\u062a\\u0642\\u062f\\u064a\\u0645 \\u0637\\u0644\\u0628\":\"0\",\"\\u062b\\u0645\\u0646 \\u0627\\u0644\\u0639\\u062f\\u0627\\u062f\":\"0\",\"\\u062b\\u0645\\u0646 \\u0645\\u0631\\u0627\\u0628\\u0637\":\"0\",\"\\u0644\\u0648\\u0627\\u0632\\u0645 \\u062a\\u0645\\u062f\\u064a\\u062f\":\"0\"}","owner_name":""},
{"pk_i_id":"47","capacity":"0","ampere":"0","customer_type":"i","fk_i_customer_id":"199","s_mobile":"0597169898","BusinessName":"","AddressDetailsAR":"البصة والخنادق   ","d_lat":"0","d_lng":"0","ownership_type":"1","owner_type":"1","owner_id":"99","licno":"","fk_i_created_by":"7","dt_created_at":"2022-03-23 08:55:41","fk_i_dept_id":"8","customer_name":"ضياء محمد سليمان دار شامي","s_attach1":"","s_attach2":"","connected_to":"0","ReciptNo":null,"AmountInNIS":null,"json_fees":"{\"\\u0631\\u0633\\u0648\\u0645 \\u0627\\u0644\\u0627\\u0634\\u062a\\u0631\\u0627\\u0643\":\"800\",\"\\u062b\\u0645\\u0646 \\u0627\\u0644\\u0639\\u062f\\u0627\\u062f\":\"0\"}","owner_name":""},
{"pk_i_id":"48","capacity":"0","ampere":"0","customer_type":"i","fk_i_customer_id":"944","s_mobile":"0568721204","BusinessName":"","AddressDetailsAR":"   منطقة الحبايل الشرقية ب خطر ","d_lat":"0","d_lng":"0","ownership_type":"1","owner_type":"9","owner_id":"44","licno":"","fk_i_created_by":"8","dt_created_at":"2022-03-26 12:13:07","fk_i_dept_id":"8","customer_name":"عبد الرحيم محمد عبد الرحيم مخلوف","s_attach1":"","s_attach2":"","connected_to":"0","ReciptNo":null,"AmountInNIS":null,"json_fees":"{\"\\u0631\\u0633\\u0648\\u0645 \\u0627\\u0644\\u0627\\u0634\\u062a\\u0631\\u0627\\u0643\":\"0\",\"\\u062b\\u0645\\u0646 \\u0627\\u0644\\u0639\\u062f\\u0627\\u062f\":\"0\"}","owner_name":""},
{"pk_i_id":"49","capacity":"0","ampere":"0","customer_type":"i","fk_i_customer_id":"946","s_mobile":"0569997799","BusinessName":"","AddressDetailsAR":"تحت العراق   كسارة ابو عصام طريق فقاس","d_lat":"0","d_lng":"0","ownership_type":"1","owner_type":"9","owner_id":"46","licno":"","fk_i_created_by":"7","dt_created_at":"2022-03-27 12:17:54","fk_i_dept_id":"8","customer_name":"شركة عصيرة القبلية للمقالع والتعهدات العامة","s_attach1":"","s_attach2":"","connected_to":"0","ReciptNo":null,"AmountInNIS":null,"json_fees":"{\"\\u0631\\u0633\\u0648\\u0645 \\u0627\\u0644\\u0627\\u0634\\u062a\\u0631\\u0627\\u0643\":\"800\",\"\\u062b\\u0645\\u0646 \\u0627\\u0644\\u0639\\u062f\\u0627\\u062f\":\"0\"}","owner_name":""}
]